[
   {
      "title": "How Much Plastic is in the Ocean?",
      "artist": "Plastic",
      "url":"https://www.seeker.com/how-much-plastic-is-in-the-ocean-1765072162.html",
      "image":"https://assets3.thrillist.com/v1/image/2359483/size/sk-2017_04_article_main_desktop_2x.jpg",
    "thumbnail_image":"https://assets3.thrillist.com/v1/image/2359481/size/sk-2017_04_article_main_desktop_2x.jpg"
   },
   {
      "title": "Humans Kill Themselves",
      "artist": "Destroy",
      "url": "https://read01.com/xGg868.html",
      "image": "https://i1.read01.com/uploads/0FbV7wupz8.jpg",
      "thumbnail_image": "https://i2.read01.com/uploads/0FbV7wglpu.jpg"
   },
   {
      "title": "World Ocean Day",
      "artist": "Save",
      "url": "https://read01.com/BoN45K.html",
      "image": "https://i1.read01.com/uploads/0DWBCjPnpD.jpg",
      "thumbnail_image": "https://i.imgur.com/K3KJ3w4h.jpg"
   },
   {
      "title": "Painful Animals",
      "artist": "不尋常的生態",
      "url": "https://www.amazon.com/Red-Taylor-Swift/dp/B008XNZMOU",
      "image": "https://i1.read01.com/uploads/0FneggaEp4.jpg",
      "thumbnail_image": "https://i1.read01.com/uploads/0Fneggd706.jpg"
   },
   {
      "title": "SharkDeffense",
      "artist": "Gene Mutation",
      "url": "http://www.zhenlieqi.com/dongwu/6886.html",
      "image": "http://www.zhenlieqi.com/uploads/allimg/16/1-16110QA603a0.jpg",
      "thumbnail_image": "http://www.zhenlieqi.com/uploads/allimg/16/1-16110QA54EK.jpg"
   }
]